<?xml version="1.0" encoding="utf-8"?>
<!DOCTYPE softwarelist SYSTEM "softwarelist.dtd">
<softwarelist name="neogeo" description="SNK Neo-Geo Cartridges">
  <software name="ladder">
    <description>Scorpion Engine game for Neo Geo</description>
    <year>2025</year>
    <publisher>PixelGlass</publisher>
    <sharedfeat name="release" value="MVS,AES" />
    <sharedfeat name="compatibility" value="MVS,AES" />
    <part name="cart" interface="neo_cart">
      <dataarea name="maincpu" width="16" endianness="big" size="0x100000">
        <rom loadflag="load16_word_swap" name="scorpion.p1" offset="0x000000" size="0x080000" crc="880fb43a" sha1="90e7823bc508bab254d0ac9885ad108c7c540d91" />
      </dataarea>
      <dataarea name="fixed" size="0x020000">
        <rom name="scorpion.s1" offset="0x000000" size="0x020000" crc="c7dc3860" sha1="be52e4663919c50e9c27fd4599fcff23411716f3" />
      </dataarea>
      <dataarea name="sprites" size="0x800000">
        <rom loadflag="load16_byte" name="scorpion.c1" offset="0x000000" size="0x020000" crc="9fe8e5d4" sha1="c679b18e448358c4e9bd5fc77ea4373d4fce69fc" />
        <rom loadflag="load16_byte" name="scorpion.c2" offset="0x000001" size="0x020000" crc="f0ea27d6" sha1="96f12dca91946f30fc4aced46d493d1b96e006eb" />
      </dataarea>
      <dataarea name="audiocpu" size="0x020000">
        <rom name="mzs_driver.m1" offset="0x000000" size="0x010000" crc="be9b2861" sha1="73fcdb56593fe06ef93b1a3bbf94d3b79f1d192c" />
      </dataarea>
      <dataarea name="ymsnd" size="0x400000">
        <rom name="scorpion.v1" offset="0x000000" size="0x020000" crc="7ee8cdcd" sha1="67dfd19f3eb3649d6f3f6631e44d0bd36b8d8d19" />
      </dataarea>
    </part>
  </software>
</softwarelist>